{
  "ear": "пель",
  "early": "ранчӧй",
  "earth": "медӧм",
  "easy": "лёгкӧй",
  "egg": "карӧч",
  "either": "кыкныт",
  "elbow": "куек",
  "email": "электронлӧй почта",
  "end": "тодмо",
  "equal": "равнӧй",
  "exact": "точнӧй",
  "exam": "экзамен",
  "excellent": "отличнӧй",
  "expensive": "дорогӧй",
  "eye": "син",
  "face": "чӧр",
  "fail": "пӧраськины",
  "fair": "справедливнӧй",
  "fall": "лопаны",
  "far": "лӧнӧ",
  "fast": "шудӧй",
  "father": "атысь",
  "few": "этша",
  "fifteen": "витляд",
  "fifty": "вита",
  "finger": "шпал",
  "fire": "ув",
  "first": "пӧзь",
  "fish": "чери",
  "fly": "лэбны",
  "flower": "лыдз",
  "floor": "джодж",
  "food": "удж",
  "foot": "кок пыдӧс",
  "foreign": "иностранын",
  "forest": "парма",
  "fork": "вида",
  "form": "форма",
  "free": "свободнӧй",
  "friend": "уналӧм",
  "funny": "асӧм",
  "garden": "сад",
  "German": "немецкӧй",
  "get": "венчӧны",
  "give": "сетны",
  "glad": "радӧй",
  "go": "мунны",
  "god": "Ен",
  "good": "бур",
  "goodbye": "аддзисьлытӧдз",
  "green": "зелён",
  "group": "группа",
  "guilty": "виновнӧй",
  "hair": "си",
  "hand": "ки",
  "happy": "сӧй",
  "hard": "ӧтись кытш",
  "have": "имны",
  "head": "юр",
  "hear": "кывны",
  "heart": "лыд",
  "heavy": "сьӧкыд",
  "here": "тані",
  "high": "высокӧй",
  "home": "ортчиды",
  "horse": "водзь",
  "hot": "ветлан",
  "house": "керка",
  "how": "кыдзи",
  "hundred": "ся",
  "hungry": "голоднӧй",
  "ice": "йи",
  "important": "важнӧй",
  "improve": "улучшыны",
  "inside": "шидзи",
  "into": "вълӧ",
  "iron": "йӧр",
  "it": "сійӧ",
  "its": "ес",
  "jump": "угӧрны",
  "just": "тӧдьы",
  "keep": "берегтыны",
  "kill": "вины",
  "kitchen": "инпöв",
  "knee": "пидзӧс",
  "know": "тӧдны",
  "lake": "ты",
  "land": "мед",
  "language": "кыв",
  "learn": "уретны",
  "leave": "выляны",
  "leg": "кок",
  "let": "пусцӧны",
  "listen": "выжны",
  "little": "кичанӧй",
  "live": "войны",
  "long": "кузь",
  "look": "тырны",
  "love": "радейтыны",
  "lunch": "ланч",
  "make": "лӧдын",
  "man": "ай",
  "many": "уна",
  "milk": "мол",
  "money": "витнянь",
  "moon": "мӧй",
  "morning": "лыӧм",
  "mother": "анась",
  "mountain": "палӧс",
  "mouth": "вом",
  "move": "пельны",
  "much": "ӧтись",
  "music": "ӧвсӧм",
  "must": "ӧйа налӧ",
  "my": "мӧй",
  "name": "лым",
  "near": "пырӧз",
  "neck": "куял",
  "new": "новӧй",
  "night": "вой",
  "nine": "ӧкмыс",
  "no": "абу",
  "nose": "ныр",
  "not": "абу",
  "now": "ныне",
  "one": "одӧк",
  "only": "толькӧ",
  "our": "мия",
  "out": "лыв",
  "outside": "шидзи",
  "over": "вӧр",
  "own": "ӧтись"
}
